PyReQTL/__init__.py
PyReQTL/annotate.py
PyReQTL/common.py
PyReQTL/gene_matrix.py
PyReQTL/harmonize_matrices.py
PyReQTL/run_matrix_ReQTL.py
PyReQTL/vaf_matrix.py
PyReQTL-0.4.0.dist-info/LICENSE
PyReQTL-0.4.0.dist-info/METADATA
PyReQTL-0.4.0.dist-info/WHEEL
PyReQTL-0.4.0.dist-info/top_level.txt
PyReQTL-0.4.0.dist-info/RECORD
