Metadata-Version: 2.1
Name: PyReQTL
Version: 0.4.0
Summary: A python library equivalent to R ReQTL Toolkit.
Home-page: https://github.com/nalomran/PyReQTL
Author: Nawaf Alomran
Author-email: nawafalomran@hotmail.com
License: UNKNOWN
Download-URL: https://github.com/nalomran/PyReQTL/archive/PyReQTL-0.1.0.tar.gz
Platform: UNKNOWN
Classifier: Environment :: Console
Classifier: Intended Audience :: Science/Research
Classifier: Intended Audience :: Developers
Classifier: Intended Audience :: Information Technology
Classifier: License :: OSI Approved :: MIT License
Classifier: Natural Language :: English
Classifier: Programming Language :: Python :: 3
Classifier: Topic :: Scientific/Engineering :: Bio-Informatics
Classifier: Topic :: Scientific/Engineering :: Information Analysis
Requires-Python: >=3.5
Requires-Dist: attrs (==20.2.0)
Requires-Dist: certifi (==2020.6.20)
Requires-Dist: cffi (==1.14.2)
Requires-Dist: importlib-metadata (==1.7.0)
Requires-Dist: iniconfig (==1.0.1)
Requires-Dist: Jinja2 (==2.11.2)
Requires-Dist: MarkupSafe (==1.1.1)
Requires-Dist: more-itertools (==8.5.0)
Requires-Dist: mypy (==0.782)
Requires-Dist: mypy-extensions (==0.4.3)
Requires-Dist: numpy (==1.19.1)
Requires-Dist: packaging (==20.4)
Requires-Dist: pandas (==1.1.2)
Requires-Dist: pluggy (==0.13.1)
Requires-Dist: py (==1.9.0)
Requires-Dist: pycparser (==2.20)
Requires-Dist: pyparsing (==2.4.7)
Requires-Dist: pytest (==6.0.1)
Requires-Dist: python-dateutil (==2.8.1)
Requires-Dist: pytz (==2020.1)
Requires-Dist: rpy2 (==3.3.5)
Requires-Dist: scipy (==1.5.2)
Requires-Dist: six (==1.15.0)
Requires-Dist: toml (==0.10.1)
Requires-Dist: typed-ast (==1.4.1)
Requires-Dist: typing-extensions (==3.7.4.3)
Requires-Dist: tzlocal (==2.1)
Requires-Dist: zipp (==3.1.0)
